mcr2/__init__.py
mcr2/losses/__init__.py
mcr2/losses/ctrl.py
mcr2/losses/mcr2.py
mcr2/primitives/__init__.py
mcr2/primitives/coding_rate.py
mcr2/primitives/logdet.py
mcr2/primitives/products.py
mcr2/primitives/statistics.py
mcr2-1.0.2.dist-info/LICENSE
mcr2-1.0.2.dist-info/METADATA
mcr2-1.0.2.dist-info/WHEEL
mcr2-1.0.2.dist-info/top_level.txt
mcr2-1.0.2.dist-info/RECORD
