Metadata-Version: 2.1
Name: mcr2
Version: 1.0.2
Summary: A performant implementation of the principle of Maximum Coding Rate Reduction (MCR2).
Home-page: https://github.com/druvpai/MCR2
Author: Druv Pai
Author-email: druvpai@berkeley.edu
Project-URL: Bug Tracker, https://github.com/druvpai/MCR2/issues
Classifier: Programming Language :: Python :: 3
Classifier: License :: OSI Approved :: MIT License
Classifier: Operating System :: OS Independent
Requires-Python: >=3.6
License-File: LICENSE
